yttp/__init__.py
yttp/http.py
yttp/reader.py
yttp/stdio_transport.py
yttp/transport.py
yttp/utils.py
yttp/writer.py
yttp/yttp_parser.py
yttp-0.0.2.dist-info/METADATA
yttp-0.0.2.dist-info/WHEEL
yttp-0.0.2.dist-info/top_level.txt
yttp-0.0.2.dist-info/RECORD
