Metadata-Version: 2.4
Name: yttp
Version: 0.0.2
Summary: Add your description here
Requires-Python: >=3.13
Requires-Dist: h11>=0.16.0
Requires-Dist: httptools>=0.6.4
Requires-Dist: pytest>=8.4.2
Requires-Dist: pytest-asyncio>=1.1.0
Requires-Dist: pytest-cov>=6.2.1
Requires-Dist: uvloop>=0.21.0
Requires-Dist: ybase>=0.0.6
